pycrc/__init__.py
pycrc/__main__.py
pycrc/algorithms.py
pycrc/codegen.py
pycrc/expr.py
pycrc/main.py
pycrc/models.py
pycrc/opt.py
pycrc/symtable.py
pycrc-0.9.2.dist-info/AUTHORS
pycrc-0.9.2.dist-info/COPYING
pycrc-0.9.2.dist-info/METADATA
pycrc-0.9.2.dist-info/WHEEL
pycrc-0.9.2.dist-info/top_level.txt
pycrc-0.9.2.dist-info/RECORD
