Metadata-Version: 2.1
Name: pycrc
Version: 0.9.2
Summary: Free, easy to use Cyclic Redundancy Check source code generator for C/C++
Home-page: https://pycrc.org
Author: Thomas Pircher
Author-email: tehpeh-web@tty1.net
License: UNKNOWN
Platform: UNKNOWN
Classifier: Programming Language :: Python :: 3
Classifier: License :: OSI Approved :: MIT License
Classifier: Operating System :: OS Independent
Requires-Python: >=3.4
